LICENSE
README.md
setup.py
tap_uservoice/__init__.py
tap_uservoice/catalog.py
tap_uservoice/client.py
tap_uservoice/config.py
tap_uservoice/schemas.py
tap_uservoice/state.py
tap_uservoice.egg-info/PKG-INFO
tap_uservoice.egg-info/SOURCES.txt
tap_uservoice.egg-info/dependency_links.txt
tap_uservoice.egg-info/entry_points.txt
tap_uservoice.egg-info/requires.txt
tap_uservoice.egg-info/top_level.txt
tap_uservoice/streams/__init__.py
tap_uservoice/streams/base.py
tap_uservoice/streams/categories.py
tap_uservoice/streams/comments.py
tap_uservoice/streams/external_accounts.py
tap_uservoice/streams/external_users.py
tap_uservoice/streams/feature_statuses.py
tap_uservoice/streams/features.py
tap_uservoice/streams/forums.py
tap_uservoice/streams/labels.py
tap_uservoice/streams/nps_ratings.py
tap_uservoice/streams/product_areas.py
tap_uservoice/streams/requests.py
tap_uservoice/streams/segmented_values.py
tap_uservoice/streams/segments.py
tap_uservoice/streams/status_updates.py
tap_uservoice/streams/statuses.py
tap_uservoice/streams/suggestions.py
tap_uservoice/streams/supporters.py
tap_uservoice/streams/teams.py
tap_uservoice/streams/users.py