Metadata-Version: 1.1
Name: tap-uservoice
Version: 1.0.4
Summary: Singer.io tap for extracting data from the Uservoice API
Home-page: http://fishtownanalytics.com
Author: Fishtown Analytics
Author-email: UNKNOWN
License: UNKNOWN
Platform: UNKNOWN
Classifier: Programming Language :: Python :: 3 :: Only
